nlputils.py
nlputils_py-0.1.2.dist-info/LICENSE
nlputils_py-0.1.2.dist-info/METADATA
nlputils_py-0.1.2.dist-info/WHEEL
nlputils_py-0.1.2.dist-info/top_level.txt
nlputils_py-0.1.2.dist-info/RECORD
