Metadata-Version: 2.1
Name: nlputils-py
Version: 0.1.2
Summary: A small and general nlp util collection for nlper
Home-page: https://github.com/codemayq/nlputils-py
Author: codingma
Author-email: codingma@163.com
License: MIT
Platform: UNKNOWN
Classifier: License :: OSI Approved :: MIT License
Classifier: Programming Language :: Python
Classifier: Programming Language :: Python :: 3
Classifier: Programming Language :: Python :: 3.6
Classifier: Programming Language :: Python :: Implementation :: CPython
Classifier: Programming Language :: Python :: Implementation :: PyPy
Requires-Python: >=3.6.0
Requires-Dist: openccpy
